.gitignore
README.md
customize.py
pyproject.toml
requirements-dev.txt
requirements.txt
setup.cfg
setup.py
.github/workflows/CI.template
.github/workflows/CI.yml.bak
.github/workflows/publish.yml
assets/dimport_nb.png
assets/dimport_py.png
dimport/__init__.py
dimport/_version.py
dimport/torch.py
dimport.egg-info/PKG-INFO
dimport.egg-info/SOURCES.txt
dimport.egg-info/dependency_links.txt
dimport.egg-info/requires.txt
dimport.egg-info/top_level.txt
tests/__init__.py