Metadata-Version: 2.1
Name: dimport
Version: 1.0.0
Summary: example description
Home-page: https://github.com/patel-zeel/dimport
Author: Zeel B Patel
Author-email: patel_zeel@iitgn.ac.in
License: MIT
Requires-Python: >=3.6
Requires-Dist: numpy
Requires-Dist: pandas
Requires-Dist: matplotlib
Requires-Dist: tqdm[notebook]
Requires-Dist: joblib
